[
  {
    "model": "reduction_viewer.status",
    "pk": 1,
    "fields": {
      "value": "q"
    }
  },
  {
    "model": "reduction_viewer.status",
    "pk": 2,
    "fields": {
      "value": "p"
    }
  },
  {
    "model": "reduction_viewer.status",
    "pk": 3,
    "fields": {
      "value": "e"
    }
  },
  {
    "model": "reduction_viewer.status",
    "pk": 4,
    "fields": {
      "value": "s"
    }
  },
  {
    "model": "reduction_viewer.status",
    "pk": 5,
    "fields": {
      "value": "c"
    }
  }
]